hungarianalg/__init__.py
hungarianalg/alg.py
hungarianalg-0.0.1.dist-info/LICENSE
hungarianalg-0.0.1.dist-info/METADATA
hungarianalg-0.0.1.dist-info/WHEEL
hungarianalg-0.0.1.dist-info/top_level.txt
hungarianalg-0.0.1.dist-info/RECORD
