Metadata-Version: 2.1
Name: hungarianalg
Version: 0.0.1
Summary: Implementation of the Hungarian Algorithm for optimal matching in bipartite weighted graphs.
Home-page: https://github.com/jbrightuniverse/hungarianalg
Author: James Yuming Yu
Author-email: UNKNOWN
License: MIT
Platform: UNKNOWN
Requires-Dist: numpy
